chill_streams/__about__.py
chill_streams/__init__.py
chill_streams/app.py
chill_streams/ascii_art.py
chill_streams/cli.py
chill_streams/cmd.py
chill_streams/config.py
chill_streams/logging.py
chill_streams/pkg_resources.py
chill_streams/script_path.py
chill_streams/shell_script.py
chill_streams/station_list.py
chill_streams/url.py
chill_streams/version.py
chill_streams/video_streams.py
chill_streams/vlc.py
chill_streams/data/__init__.py
chill_streams/data/https.txt
chill_streams/data/stations.csv
chill_streams/data/videostreams.csv
chill_streams/data/vlc-radio-template.sh
Chill_Streams-0.4.4.dist-info/LICENSE
Chill_Streams-0.4.4.dist-info/METADATA
Chill_Streams-0.4.4.dist-info/WHEEL
Chill_Streams-0.4.4.dist-info/entry_points.txt
Chill_Streams-0.4.4.dist-info/top_level.txt
Chill_Streams-0.4.4.dist-info/RECORD
