Metadata-Version: 2.1
Name: Chill-Streams
Version: 0.4.4
Summary: Chill electronica streaming
Home-page: https://github.com/zcutlip/chill_streams
Author: Zachary Cutlip
Author-email: uid000@gmail.com
License: MIT
Requires-Python: >=3.10
License-File: LICENSE
Requires-Dist: python-singleton-metaclasses
Provides-Extra: video-streams
Requires-Dist: streamlink ; extra == 'video-streams'
